setup.py
Yoav.egg-info/PKG-INFO
Yoav.egg-info/SOURCES.txt
Yoav.egg-info/dependency_links.txt
Yoav.egg-info/requires.txt
Yoav.egg-info/top_level.txt
yoav/__init__.py
yoav/version.py
yoav/yslient.py