Metadata-Version: 1.1
Name: Yoav
Version: 0.2.1
Summary: Yoavs Test Library
Home-page: UNKNOWN
Author: Yoav Schatzberg
Author-email: UNKNOWN
License: UNKNOWN
Platform: UNKNOWN
Classifier: Programming Language :: Python
Classifier: Development Status :: 4 - Beta
Classifier: Intended Audience :: Developers
Classifier: License :: OSI Approved :: MIT License
Classifier: Topic :: Software Development :: Libraries :: Python Modules
